pyprince/__init__.py
pyprince/pyprince.py
pyprince-0.6.1.dist-info/LICENSE
pyprince-0.6.1.dist-info/METADATA
pyprince-0.6.1.dist-info/WHEEL
pyprince-0.6.1.dist-info/top_level.txt
pyprince-0.6.1.dist-info/RECORD
