Metadata-Version: 2.1
Name: pyprince
Version: 0.6.1
Summary: Prince xml python wrapper for converting HTML to PDF
Home-page: https://github.com/sufio/python-pyprince
Author: Sufio.com
Author-email: sufio@sufio.com
License: MIT
License-File: LICENSE
